somelang/__init__.py
somelang/__main__.py
somelang/default_patterns.py
somelang/default_trigrams.py
somelang/default_whitelist.py
somelang/somelang.py
somelang-0.0.3.dist-info/licenses/LICENSE
somelang-0.0.3.dist-info/METADATA
somelang-0.0.3.dist-info/WHEEL
somelang-0.0.3.dist-info/top_level.txt
somelang-0.0.3.dist-info/RECORD
