Metadata-Version: 2.4
Name: somelang
Version: 0.0.3
Summary: Language Detection Library
Home-page: https://github.com/SomeAB/somelang
Author: SomeAB
Author-email: SomeAB <ssabs@protonmail.com>
License: MIT License
Project-URL: Homepage, https://github.com/SomeAB/somelang
Project-URL: Bug Reports, https://github.com/SomeAB/somelang/issues
Project-URL: Source, https://github.com/SomeAB/somelang
Keywords: language detection,nlp,text analysis,linguistics
Classifier: Development Status :: 1 - Planning
Classifier: Intended Audience :: Developers
Classifier: Topic :: Text Processing :: Linguistic
Classifier: License :: OSI Approved :: MIT License
Classifier: Programming Language :: Python :: 3
Classifier: Programming Language :: Python :: 3.8
Classifier: Programming Language :: Python :: 3.9
Classifier: Programming Language :: Python :: 3.10
Classifier: Programming Language :: Python :: 3.11
Classifier: Programming Language :: Python :: 3.12
Requires-Python: >=3.8
License-File: LICENSE
Dynamic: author
Dynamic: home-page
Dynamic: license-file
Dynamic: requires-python
